storage_device_managers/__init__.py
storage_device_managers/py.typed
storage_device_managers-0.15.0.dist-info/LICENSE
storage_device_managers-0.15.0.dist-info/METADATA
storage_device_managers-0.15.0.dist-info/WHEEL
storage_device_managers-0.15.0.dist-info/RECORD
