Metadata-Version: 2.1
Name: storage-device-managers
Version: 0.15.0
Summary: Helpful context managers for managing decryption and mounts of storage devices
Home-page: https://github.com/MaxG87/storage-device-managers
License: GPL-3.0-or-later
Author: Max Görner
Author-email: 5477952+MaxG87@users.noreply.github.com
Requires-Python: >=3.8.1,<3.13
Classifier: License :: OSI Approved :: GNU General Public License v3 or later (GPLv3+)
Classifier: Programming Language :: Python :: 3
Classifier: Programming Language :: Python :: 3.9
Classifier: Programming Language :: Python :: 3.10
Classifier: Programming Language :: Python :: 3.11
Classifier: Programming Language :: Python :: 3.12
Provides-Extra: logging
Requires-Dist: loguru (>=0.7.2,<0.8.0) ; extra == "logging"
Requires-Dist: shell-interface (>=0.13.0,<0.14.0)
Project-URL: Repository, https://github.com/MaxG87/storage-device-managers
